libvmake/__init__.py
libvmake/__main__.py
libvmake/libvmake.py
libvmake/utils.py
libvmake/__pycache__/__init__.cpython-39.pyc
libvmake/res/elevate.exe
libvmake/res/gsudo.exe
libvmake-2.0.0.dist-info/LICENCE
libvmake-2.0.0.dist-info/METADATA
libvmake-2.0.0.dist-info/WHEEL
libvmake-2.0.0.dist-info/top_level.txt
libvmake-2.0.0.dist-info/RECORD
